goblin_lite/LCA_processing/__init__.py
goblin_lite/LCA_processing/crop_lca_generator.py
goblin_lite/LCA_processing/landuse_lca_generator.py
goblin_lite/LCA_processing/lca_total_generator.py
goblin_lite/LCA_processing/livestock_lca_generator.py
goblin_lite/__init__.py
goblin_lite/data_processing/__init__.py
goblin_lite/data_processing/animal_data_generation.py
goblin_lite/data_processing/crop_data_generator.py
goblin_lite/data_processing/forest_carbon_generator.py
goblin_lite/data_processing/grassland_data_generation.py
goblin_lite/data_processing/landuse_data_generator.py
goblin_lite/database/__init__.py
goblin_lite/database/goblin_database.db
goblin_lite/goblin.py
goblin_lite/impact_categories/__init__.py
goblin_lite/impact_categories/air_quality.py
goblin_lite/impact_categories/climate_change.py
goblin_lite/impact_categories/common.py
goblin_lite/impact_categories/eutrophication.py
goblin_lite/resource_manager/__init__.py
goblin_lite/resource_manager/data_fetcher.py
goblin_lite/resource_manager/database_manager.py
goblin_lite/resource_manager/directory.py
goblin_lite/resource_manager/goblin_data_manager.py
goblin_lite/resource_manager/scenario_data_fetcher.py
goblin_lite/scenario_analysis/__init__.py
goblin_lite/scenario_analysis/data_grapher.py
goblin_lite-0.5.0.dist-info/LICENSE
goblin_lite-0.5.0.dist-info/METADATA
goblin_lite-0.5.0.dist-info/WHEEL
goblin_lite-0.5.0.dist-info/RECORD
