Metadata-Version: 2.1
Name: goblin_lite
Version: 0.5.0
Summary: A goblin tool for the generation of static land balance scenarios and environmental impacts
License: GPL-3.0
Author: Colm Duffy
Requires-Python: >=3.9,<4.0
Classifier: License :: OSI Approved :: GNU General Public License v3 (GPLv3)
Classifier: Programming Language :: Python :: 3
Classifier: Programming Language :: Python :: 3.9
Classifier: Programming Language :: Python :: 3.10
Classifier: Programming Language :: Python :: 3.11
Classifier: Programming Language :: Python :: 3.12
Requires-Dist: cattle_lca (>=0.3.1,<0.4.0)
Requires-Dist: crop_lca (>=0.2.1,<0.3.0)
Requires-Dist: goblin_cbm_runner (>=0.5.0,<0.6.0)
Requires-Dist: grassland_production (>=0.3.6,<0.4.0)
Requires-Dist: landcover_assignment (>=0.4.0,<0.5.0)
Requires-Dist: landcover_lca (>=0.2.0,<0.3.0)
Requires-Dist: livestock_generation (>=0.2.1,<0.3.0)
Requires-Dist: matplotlib
Requires-Dist: numpy (>=1.25.0,<2.0.0)
Requires-Dist: pandas (==2.1.4)
Requires-Dist: scenario_assessment (>=0.1.3,<0.2.0)
Requires-Dist: seaborn (>=0.13.1,<0.14.0)
Requires-Dist: sheep_lca (>=0.3.1,<0.4.0)
Requires-Dist: sqlalchemy-utils
Requires-Dist: static_scenario_generator (>=1.1.1,<2.0.0)
